zorg_network_camera-0.0.3.dist-info/RECORD
zorg_network_camera-0.0.3.dist-info/top_level.txt
zorg_network_camera-0.0.3.dist-info/metadata.json
zorg_network_camera-0.0.3.dist-info/zip-safe
zorg_network_camera-0.0.3.dist-info/METADATA
zorg_network_camera-0.0.3.dist-info/DESCRIPTION.rst
zorg_network_camera-0.0.3.dist-info/WHEEL
tests/test_drivers.py
tests/__init__.py
tests/test_adaptor.py
tests/smoke_tests/test_commands.py
tests/smoke_tests/__init__.py
tests/smoke_tests/test_serializers.py
zorg_network_camera/light_sensor.py
zorg_network_camera/feed.py
zorg_network_camera/ocr.py
zorg_network_camera/adaptor.py
zorg_network_camera/__init__.py
