Metadata-Version: 2.0
Name: zorg-network-camera
Version: 0.0.3
Summary: A module which includes various network camera utilities.
Home-page: https://github.com/zorg/zorg-network-camera
Author: Zorg Group
Author-email: gunthercx@gmail.com
License: MIT
Keywords: zorg,network,ip,camera
Platform: any
Classifier: Development Status :: 4 - Beta
Classifier: Intended Audience :: Developers
Classifier: License :: OSI Approved :: BSD License
Classifier: Environment :: Console
Classifier: Environment :: Web Environment
Classifier: Operating System :: OS Independent
Classifier: Programming Language :: Python
Classifier: Programming Language :: Python :: 2.7
Classifier: Programming Language :: Python :: 3
Classifier: Programming Language :: Python :: 3.3
Classifier: Programming Language :: Python :: 3.4
Requires-Dist: zorg (>=0.0.1)
Requires-Dist: pillow (>=3.0.0)
Requires-Dist: pytesseract (==0.1.6)
